{
  "structureId": "#nova_structures:shrine",
  "spawnerProperties": [
    {
      "blockEntityTypesToReplace": ["minecraft:trial_spawner"],
      "mobEntitiesInSpawnerToReplace": ["minecraft:breeze"],
      "lootTables": [],
      "ominousLootTables": [],
      "listOfPokemonToSpawn": [{
        "species": "charizard",
        "weight": 50,
        "level": 30
      },
      {
        "species": "charizard",
        "weight": 50,
        "level": 30
      }],
      "listOfOminousPokemonToSpawn": [{
        "species": "charizard",
        "weight": 50,
        "level": 60
      },
      {
        "species": "charizard",
        "weight": 50,
        "level": 60
      }]
    },
    {
      "blockEntityTypesToReplace": ["minecraft:trial_spawner"],
      "mobEntitiesInSpawnerToReplace": ["minecraft:zombie"],
      "lootTables": [],
      "ominousLootTables": [],
      "listOfPokemonToSpawn": [{
        "species": "charizard",
        "weight": 50,
        "level": 30
      },
      {
        "species": "charizard",
        "weight": 50,
        "level": 30
      }],
      "listOfOminousPokemonToSpawn": [{
        "species": "charizard",
        "weight": 50,
        "level": 60
      },
      {
        "species": "charizard",
        "weight": 50,
        "level": 60
      }]
    },
    {
      "blockEntityTypesToReplace": ["minecraft:trial_spawner"],
      "mobEntitiesInSpawnerToReplace": ["minecraft:husk"],
      "lootTables": [],
      "ominousLootTables": [],
      "listOfPokemonToSpawn": [{
        "species": "charizard",
        "weight": 50,
        "level": 30
      },
      {
        "species": "charizard",
        "weight": 50,
        "level": 30
      }],
      "listOfOminousPokemonToSpawn": [{
        "species": "charizard",
        "weight": 50,
        "level": 60
      },
      {
        "species": "charizard",
        "weight": 50,
        "level": 60
      }]
    },
    {
      "blockEntityTypesToReplace": ["minecraft:trial_spawner"],
      "mobEntitiesInSpawnerToReplace": ["minecraft:spider"],
      "lootTables": [],
      "ominousLootTables": [],
      "listOfPokemonToSpawn": [{
        "species": "charizard",
        "weight": 50,
        "level": 30
      },
      {
        "species": "charizard",
        "weight": 50,
        "level": 30
      }],
      "listOfOminousPokemonToSpawn": [{
        "species": "charizard",
        "weight": 50,
        "level": 60
      },
      {
        "species": "charizard",
        "weight": 50,
        "level": 60
      }]
    },
    {
      "blockEntityTypesToReplace": ["minecraft:trial_spawner"],
      "mobEntitiesInSpawnerToReplace": ["minecraft:slime"],
      "lootTables": [],
      "ominousLootTables": [],
      "listOfPokemonToSpawn": [{
          "species": "charizard",
          "weight": 50,
          "level": 30
        },
        {
          "species": "charizard",
          "weight": 50,
          "level": 30
        }],
      "listOfOminousPokemonToSpawn": [{
          "species": "charizard",
          "weight": 50,
          "level": 60
        },
        {
          "species": "charizard",
          "weight": 50,
          "level": 60
        }]
    },
    {
      "blockEntityTypesToReplace": ["minecraft:trial_spawner"],
      "mobEntitiesInSpawnerToReplace": ["minecraft:silverfish"],
      "lootTables": [],
      "ominousLootTables": [],
      "listOfPokemonToSpawn": [{
        "species": "charizard",
        "weight": 50,
        "level": 30
      },
      {
        "species": "charizard",
        "weight": 50,
        "level": 30
      }],
      "listOfOminousPokemonToSpawn": [{
        "species": "charizard",
        "weight": 50,
        "level": 60
      },
      {
        "species": "charizard",
        "weight": 50,
        "level": 60
      }]
    },
    {
      "blockEntityTypesToReplace": ["minecraft:trial_spawner"],
      "mobEntitiesInSpawnerToReplace": ["minecraft:cave_spider"],
      "lootTables": [],
      "ominousLootTables": [],
      "listOfPokemonToSpawn": [{
        "species": "charizard",
        "weight": 50,
        "level": 30
      },
      {
        "species": "charizard",
        "weight": 50,
        "level": 30
      }],
      "listOfOminousPokemonToSpawn": [{
        "species": "charizard",
        "weight": 50,
        "level": 60
      },
      {
        "species": "charizard",
        "weight": 50,
        "level": 60
      }]
    },
    {
      "blockEntityTypesToReplace": ["minecraft:trial_spawner"],
      "mobEntitiesInSpawnerToReplace": ["minecraft:stray"],
      "lootTables": [],
      "ominousLootTables": [],
      "listOfPokemonToSpawn": [{
        "species": "charizard",
        "weight": 100,
        "level": 30
      },
      {
        "species": "charizard",
        "weight": 100,
        "level": 30
      }],
      "listOfOminousPokemonToSpawn": [{
        "species": "charizard",
        "weight": 100,
        "level": 60
      },
      {
        "species": "charizard",
        "weight": 100,
        "level": 60
      }]
    },
    {
      "blockEntityTypesToReplace": ["minecraft:trial_spawner"],
      "mobEntitiesInSpawnerToReplace": ["minecraft:skeleton"],
      "lootTables": [],
      "ominousLootTables": [],
      "listOfPokemonToSpawn": [{
        "species": "charizard",
        "weight": 50,
        "level": 30
      },
      {
        "species": "charizard",
        "weight": 50,
        "level": 30
      }],
      "listOfOminousPokemonToSpawn": [{
        "species": "charizard",
        "weight": 50,
        "level": 60
      },
      {
        "species": "charizard",
        "weight": 50,
        "level": 60
      }]
    },
    {
      "blockEntityTypesToReplace": ["minecraft:trial_spawner"],
      "mobEntitiesInSpawnerToReplace": ["minecraft:bogged"],
      "lootTables": [],
      "ominousLootTables": [],
      "listOfPokemonToSpawn": [{
        "species": "charizard",
        "weight": 50,
        "level": 30
      },
      {
        "species": "charizard",
        "weight": 50,
        "level": 30
      }],
      "listOfOminousPokemonToSpawn": [{
        "species": "charizard",
        "weight": 50,
        "level": 60
      },
      {
        "species": "charizard",
        "weight": 50,
        "level": 60
      }]
    }
  ]
}